[
  {
    "name": "Tyr",
    "imageSrc": "Tyr.jpeg",
    "class": "Bard",
    "level": 1,
    "healthPoints": 7,
    "initiative": 8,
    "armorValue": 12,
    "isEnemy": false,
    "damageTaken": 0,
    "isAvailable": true
  },
  {
    "name": "Yoshi",
    "imageSrc": "Yoshi.jpeg",
    "class": "Sorcerer",
    "level": 1,
    "healthPoints": 8,
    "initiative": 23,
    "armorValue": 15,
    "isEnemy": false,
    "damageTaken": 0,
    "isAvailable": true
  },
  {
    "name": "Larry",
    "imageSrc": "Larry.jpeg",
    "class": "Rogue",
    "level": 1,
    "healthPoints": 8,
    "initiative": 3,
    "armorValue": 14,
    "isEnemy": false,
    "damageTaken": 0,
    "isAvailable": false
  },
  {
    "name": "Caronte",
    "imageSrc": "Caronte.jpeg",
    "class": "Warlock",
    "level": 1,
    "healthPoints": 9,
    "initiative": 1,
    "armorValue": 13,
    "isEnemy": false,
    "damageTaken": 0,
    "isAvailable": false
  },
  {
    "name": "Arche",
    "imageSrc": "Andres.jpeg",
    "class": "Cleric",
    "level": 1,
    "healthPoints": 11,
    "initiative": 10,
    "armorValue": 18,
    "isEnemy": false,
    "damageTaken": 0,
    "isAvailable": true
  },
  {
    "name": "Rembrandt",
    "imageSrc": "Rembrandt.png",
    "class": "Warlock",
    "level": 1,
    "healthPoints": 10,
    "initiative": 14,
    "armorValue": 14,
    "isEnemy": false,
    "damageTaken": 0,
    "isAvailable": true
  }
]
